Metadata-Version: 2.1
Name: nonebot-plugin-sayoroll
Version: 1.0.5
Summary: 基于NoneBot的高仿以前小夜bot的roll功能
Home-page: https://github.com/mas-alone/nonebot-plugin-sayoroll
Author: A M D
Author-email: mas_alone@qq.com
Classifier: Programming Language :: Python :: 3.8
Classifier: License :: OSI Approved :: GNU Affero General Public License v3
Classifier: Operating System :: OS Independent
License-File: LICENSE
Requires-Dist: nonebot2 >=2.2.0
Requires-Dist: nonebot-adapter-onebot >=2.0.0b1
Requires-Dist: nonebot-plugin-alconna >=0.38.2
